Metadata-Version: 1.1
Name: fs-dlk
Version: 0.1.3
Summary: Azure Datalake filesystem for PyFilesystem2
Home-page: https://github.com/emedgene/fs_dlk
Author: emedgene
Author-email: pypi@emedgene.com
License: MIT
Download-URL: https://github.com/emedgene/fs_dlk/tarball/0.1.3
Keywords: pyfilesystem,Azure,Datalake,dlk
Platform: any
Classifier: Development Status :: 4 - Beta
Classifier: Intended Audience :: Developers
Classifier: Operating System :: OS Independent
Classifier: Programming Language :: Python
Classifier: Programming Language :: Python :: 2.7
Classifier: Programming Language :: Python :: 3.3
Classifier: Programming Language :: Python :: 3.4
Classifier: Programming Language :: Python :: 3.5
Classifier: Programming Language :: Python :: 3.6
Classifier: Programming Language :: Python :: 3.7
Classifier: Topic :: System :: Filesystems
